menglingtool_django/__init__.py
menglingtool_django/django_tool.py
menglingtool_django/element/table/main.py
menglingtool_django/statics/css/amazeui.datatables.min.css
menglingtool_django/statics/css/amazeui.min.css
menglingtool_django/statics/css/mycss.css
menglingtool_django/statics/img/404.png
menglingtool_django/statics/js/ajax.js
menglingtool_django/statics/js/amazeui.datatables.min.js
menglingtool_django/statics/js/amazeui.min.js
menglingtool_django/statics/js/clipboard.min.js
menglingtool_django/statics/js/line.js
menglingtool_django/statics/js/main.js
menglingtool_django/statics/js/tool.js
menglingtool_django/statics/js/function/fold.js
menglingtool_django/statics/js/function/select.js
menglingtool_django/statics/js/function/windows.js
menglingtool_django-1.0.1.dist-info/METADATA
menglingtool_django-1.0.1.dist-info/WHEEL
menglingtool_django-1.0.1.dist-info/top_level.txt
menglingtool_django-1.0.1.dist-info/RECORD
